stelix/__init__.py
stelix/api.py
stelix/endpoints.py
stelix-1.0.2.dist-info/LICENSE
stelix-1.0.2.dist-info/METADATA
stelix-1.0.2.dist-info/WHEEL
stelix-1.0.2.dist-info/top_level.txt
stelix-1.0.2.dist-info/RECORD
