Metadata-Version: 2.1
Name: stelix
Version: 1.0.2
Summary: A Python wrapper for the Sellix API
Home-page: https://github.com/iclapcheeks/Seltix
Author: iclapcheeks
Author-email: iclapcheeks@seized.us
Requires-Python: ~=3.7
License-File: LICENSE
Requires-Dist: requests (<3,>=2.25.1)
